MANIFEST.in
setup.py
docs/HISTORY.txt
src/dolmen/__init__.py
src/dolmen.breadcrumbs.egg-info/PKG-INFO
src/dolmen.breadcrumbs.egg-info/SOURCES.txt
src/dolmen.breadcrumbs.egg-info/dependency_links.txt
src/dolmen.breadcrumbs.egg-info/namespace_packages.txt
src/dolmen.breadcrumbs.egg-info/not-zip-safe
src/dolmen.breadcrumbs.egg-info/requires.txt
src/dolmen.breadcrumbs.egg-info/top_level.txt
src/dolmen/breadcrumbs/README.txt
src/dolmen/breadcrumbs/__init__.py
src/dolmen/breadcrumbs/configure.zcml
src/dolmen/breadcrumbs/crumbs.py
src/dolmen/breadcrumbs/renderer.py
src/dolmen/breadcrumbs/test_breadcrumbs.txt
src/dolmen/breadcrumbs/locales/de/LC_MESSAGES/dolmen.breadcrumbs.mo
src/dolmen/breadcrumbs/locales/de/LC_MESSAGES/dolmen.breadcrumbs.po
src/dolmen/breadcrumbs/locales/fr/LC_MESSAGES/dolmen.breadcrumbs.mo
src/dolmen/breadcrumbs/locales/fr/LC_MESSAGES/dolmen.breadcrumbs.po
src/dolmen/breadcrumbs/templates/breadcrumbs.pt