Metadata-Version: 1.1
Name: dolmen.breadcrumbs
Version: 0.2.1
Summary: Breadcrumbs navigation for the Cromlech framework.
Home-page: http://gitweb.dolmen-project.org
Author: Souheil Chelfouh
Author-email: trollfot@gmail.com
License: ZPL
Keywords: Cromlech Dolmen
Platform: Any
Classifier: Environment :: Web Environment
Classifier: Intended Audience :: Other Audience
Classifier: License :: OSI Approved :: Zope Public License
Classifier: Operating System :: OS Independent
Classifier: Programming Language :: Python
